spotify_api_client/__init__.py
spotify_api_client/client.py
spotify_api_client-0.1.0.dist-info/METADATA
spotify_api_client-0.1.0.dist-info/WHEEL
spotify_api_client-0.1.0.dist-info/RECORD
