Metadata-Version: 2.1
Name: spotify-api-client
Version: 0.1.0
Summary: 
Author: William04A
Author-email: 35110380+William04A@users.noreply.github.com
Requires-Python: >=3.9,<4.0
Classifier: Programming Language :: Python :: 3
Classifier: Programming Language :: Python :: 3.9
Classifier: Programming Language :: Python :: 3.10
Classifier: Programming Language :: Python :: 3.11
Requires-Dist: requests (>=2.31.0,<3.0.0)
